LICENSE
MANIFEST.in
README.rst
setup.py
pigeon/__init__.py
pigeon/__version__.py
pigeon/annotate.py
pigeon_jupyter.egg-info/PKG-INFO
pigeon_jupyter.egg-info/SOURCES.txt
pigeon_jupyter.egg-info/dependency_links.txt
pigeon_jupyter.egg-info/requires.txt
pigeon_jupyter.egg-info/top_level.txt