Metadata-Version: 1.1
Name: pigeon-jupyter
Version: 0.1.0
Summary: Quickly annotate data on Jupyter notebooks.
Home-page: https://github.com/agermanidis/pigeon
Author: Anastasis Germanidis
Author-email: agermanidis@gmail.com
License: Apache 2.0
Platform: UNKNOWN
Classifier: Programming Language :: Python
Classifier: Programming Language :: Python :: 3
Classifier: Programming Language :: Python :: 3.3
Classifier: Programming Language :: Python :: 3.4
Classifier: Programming Language :: Python :: 3.5
Classifier: Programming Language :: Python :: 3.6
Classifier: Topic :: Scientific/Engineering :: Artificial Intelligence
Classifier: Framework :: Jupyter
